utils_api_pipefy/__init__.py
utils_api_pipefy/libs/__init__.py
utils_api_pipefy/libs/engine.py
utils_api_pipefy/libs/excepts.py
utils_api_pipefy/libs/log.py
utils_api_pipefy/libs/pipefy.py
utils_api_pipefy/libs/utilits_pipe.py
utils_api_pipefy-0.5.3.dist-info/LICENSE
utils_api_pipefy-0.5.3.dist-info/METADATA
utils_api_pipefy-0.5.3.dist-info/WHEEL
utils_api_pipefy-0.5.3.dist-info/RECORD
