Metadata-Version: 2.1
Name: utils-api-pipefy
Version: 0.5.3
Summary: Ferramentas para otimizar o consumo paralelizado de api do pipefy, trantando os retornos.
Home-page: https://github.com/YuriMotoshima/utils-api-pipefy
License: MIT
Author: Yuri Motoshima
Author-email: yurimotoshima@gmail.com
Requires-Python: >=3.9
Classifier: License :: OSI Approved :: MIT License
Classifier: Programming Language :: Python :: 3
Classifier: Programming Language :: Python :: 3.9
Classifier: Programming Language :: Python :: 3.10
Classifier: Programming Language :: Python :: 3.11
Classifier: Programming Language :: Python :: 3.12
Requires-Dist: python-dotenv (>=0.19.2)
Requires-Dist: requests (>=2.27.1)
Project-URL: GitHub, https://github.com/YuriMotoshima/utils-api-pipefy
Project-URL: Repository, https://github.com/YuriMotoshima/utils-api-pipefy
